speechmatics/__init__.py
speechmatics/sdk/__init__.py
speechmatics_sdk-0.1.1.dist-info/METADATA
speechmatics_sdk-0.1.1.dist-info/WHEEL
speechmatics_sdk-0.1.1.dist-info/top_level.txt
speechmatics_sdk-0.1.1.dist-info/RECORD
