Metadata-Version: 2.4
Name: speechmatics-sdk
Version: 0.1.1
Summary: Speechmatics Python SDK - Complete package for all Speechmatics APIs
Author-email: Speechmatics <support@speechmatics.com>
License-Expression: MIT
Project-URL: homepage, https://github.com/speechmatics/speechmatics-python-sdk
Project-URL: documentation, https://docs.speechmatics.com/
Project-URL: repository, https://github.com/speechmatics/speechmatics-python-sdk
Project-URL: issues, https://github.com/speechmatics/speechmatics-python-sdk/issues
Keywords: speechmatics,speech-to-text,tts,voice,agents,batch,real-time,transcription,api,sdk
Classifier: Development Status :: 4 - Beta
Classifier: Intended Audience :: Developers
Classifier: Programming Language :: Python :: 3
Classifier: Programming Language :: Python :: 3.9
Classifier: Programming Language :: Python :: 3.10
Classifier: Programming Language :: Python :: 3.11
Classifier: Programming Language :: Python :: 3.12
Classifier: Operating System :: OS Independent
Classifier: Topic :: Multimedia :: Sound/Audio :: Speech
Classifier: Topic :: Software Development :: Libraries :: Python Modules
Requires-Python: >=3.9
Requires-Dist: speechmatics-batch
Requires-Dist: speechmatics-rt
Requires-Dist: speechmatics-voice
Requires-Dist: speechmatics-tts
Provides-Extra: smart
Requires-Dist: speechmatics-voice[smart]; extra == "smart"
Provides-Extra: dev
Requires-Dist: black; extra == "dev"
Requires-Dist: ruff; extra == "dev"
Requires-Dist: mypy; extra == "dev"
Requires-Dist: pre-commit; extra == "dev"
Requires-Dist: pytest; extra == "dev"
Requires-Dist: pytest-asyncio; extra == "dev"
Requires-Dist: pytest-cov; extra == "dev"
Requires-Dist: pytest-mock; extra == "dev"
Requires-Dist: build; extra == "dev"
